README.md
setup.py
oidcat/__init__.py
oidcat/__version__.py
oidcat/core.py
oidcat/exceptions.py
oidcat/server.py
oidcat/token.py
oidcat/util.py
oidcat/well_known.py
oidcat.egg-info/PKG-INFO
oidcat.egg-info/SOURCES.txt
oidcat.egg-info/dependency_links.txt
oidcat.egg-info/entry_points.txt
oidcat.egg-info/requires.txt
oidcat.egg-info/top_level.txt
oidcat/cli/__init__.py
oidcat/cli/keycloak.py
oidcat/cli/util.py