Metadata-Version: 2.1
Name: oidcat
Version: 0.5.2
Summary: easy oidc client & server
Home-page: UNKNOWN
Author: Bea Steers
Author-email: bea.steers@gmail.com
License: MIT License
Platform: UNKNOWN
Provides-Extra: server
Provides-Extra: cli
